ilovetools/__init__.py
ilovetools/ai/__init__.py
ilovetools/ai/embeddings.py
ilovetools/ai/inference.py
ilovetools/ai/llm_helpers.py
ilovetools/audio/__init__.py
ilovetools/automation/__init__.py
ilovetools/conversion/__init__.py
ilovetools/data/__init__.py
ilovetools/data/feature_engineering.py
ilovetools/data/preprocessing.py
ilovetools/database/__init__.py
ilovetools/datetime/__init__.py
ilovetools/files/__init__.py
ilovetools/image/__init__.py
ilovetools/security/__init__.py
ilovetools/text/__init__.py
ilovetools/utils/__init__.py
ilovetools/validation/__init__.py
ilovetools/web/__init__.py
ilovetools-0.1.3.dist-info/licenses/LICENSE
tests/__init__.py
ilovetools-0.1.3.dist-info/METADATA
ilovetools-0.1.3.dist-info/WHEEL
ilovetools-0.1.3.dist-info/top_level.txt
ilovetools-0.1.3.dist-info/RECORD
