Metadata-Version: 2.4
Name: ilovetools
Version: 0.1.3
Summary: A comprehensive Python utility library with modular tools for AI/ML, data processing, and daily programming needs
Home-page: https://github.com/AliMehdi512/ilovetools
Author: Ali Mehdi
Author-email: Ali Mehdi <ali.mehdi.dev579@gmail.com>
License: MIT
Project-URL: Homepage, https://github.com/AliMehdi512/ilovetools
Project-URL: Repository, https://github.com/AliMehdi512/ilovetools
Project-URL: Issues, https://github.com/AliMehdi512/ilovetools/issues
Keywords: utilities,tools,ai,ml,data-processing,automation
Classifier: Development Status :: 3 - Alpha
Classifier: Intended Audience :: Developers
Classifier: Topic :: Software Development :: Libraries :: Python Modules
Classifier: License :: OSI Approved :: MIT License
Classifier: Programming Language :: Python :: 3
Classifier: Programming Language :: Python :: 3.8
Classifier: Programming Language :: Python :: 3.9
Classifier: Programming Language :: Python :: 3.10
Classifier: Programming Language :: Python :: 3.11
Classifier: Programming Language :: Python :: 3.12
Requires-Python: >=3.8
License-File: LICENSE
Dynamic: author
Dynamic: home-page
Dynamic: license-file
Dynamic: requires-python
